rtl/encoder_core.v
module encoder_core (
    input  wire        clk,
    input  wire        reset,   
    input  wire        enable,
    input  wire        enc_a,
    input  wire        enc_b,

    output reg  signed [31:0] position,
    output reg               direction
);

// Internal signals
reg signed [1:0] step;
reg [1:0] ab_prev;
reg [1:0] ab_curr;

// Combinatorial Logic to determine step
always @(*) begin
    step = 0;
    case ({ab_prev, ab_curr})
        4'b0001: step = 1;
        4'b0111: step = 1;
        4'b1110: step = 1;
        4'b1000: step = 1;
        4'b0010: step = -1;
        4'b1011: step = -1;
        4'b1101: step = -1;
        4'b0100: step = -1;
        default: step = 0;
    endcase
end

// Clocked logic to update encoder state
always @(posedge clk) begin
    if (reset) begin
        ab_prev <= 2'b00;
        ab_curr <= 2'b00;
    end else begin
        ab_prev <= ab_curr;
        ab_curr <= {enc_a, enc_b};
    end
end


// Clocked logic to update registers
always @(posedge clk) begin
    if (reset) begin
        position  <= 0;
        direction <= 0;
    end else if (enable) begin
        position  <= position + step;
        if (step == 1)
            direction <= 1'b1;
        else if (step == -1)
            direction <= 1'b0;

    end
end




endmodule

testbenches/tb_encoder_core.v
`timescale 1ns/1ps

module tb_encoder_core;

    reg clk;
    reg reset;
    reg enable;
    reg enc_a;
    reg enc_b;

    wire signed [31:0] position;
    wire direction;

    encoder_core dut (
        .clk(clk),
        .reset(reset),
        .enable(enable),
        .enc_a(enc_a),
        .enc_b(enc_b),
        .position(position),
        .direction(direction)
    );

    // 100 MHz (10 ns )
    always #5 clk = ~clk;

    initial begin
        $dumpfile("sims/encoder_wave.vcd");
        $dumpvars(0, tb_encoder_core);

        // Initialize
        clk     = 0;
        reset   = 1;
        enable  = 0;
        enc_a   = 0;
        enc_b   = 0;

        // Hold reset
        #20;
        reset  = 0;
        enable = 1;

        // Forward sequence: 00 → 01 → 11 → 10 → 00
        #10 {enc_a, enc_b} = 2'b01;
        #10 {enc_a, enc_b} = 2'b11;
        #10 {enc_a, enc_b} = 2'b10;
        #10 {enc_a, enc_b} = 2'b00;

        // Stop simulation
        #20;
        $finish;
    end

endmodule

sims/encoder_wave.vcd
$date
	Tue Dec 23 12:39:14 2025
$end
$version
	Icarus Verilog
$end
$timescale
	1ps
$end
$scope module tb_encoder_core $end
$var wire 32 ! position [31:0] $end
$var wire 1 " direction $end
$var reg 1 # clk $end
$var reg 1 $ enable $end
$var reg 1 % enc_a $end
$var reg 1 & enc_b $end
$var reg 1 ' reset $end
$scope module dut $end
$var wire 1 # clk $end
$var wire 1 $ enable $end
$var wire 1 % enc_a $end
$var wire 1 & enc_b $end
$var wire 1 ' reset $end
$var reg 2 ( ab_curr [1:0] $end
$var reg 2 ) ab_prev [1:0] $end
$var reg 1 " direction $end
$var reg 32 * position [31:0] $end
$var reg 2 + step [1:0] $end
$upscope $end
$upscope $end
$enddefinitions $end
$comment Show the parameter values. $end
$dumpall
$end
#0
$dumpvars
bx +
bx *
bx )
bx (
1'
0&
0%
0$
0#
x"
bx !
$end
#5000
b0 +
b0 (
b0 )
0"
b0 !
b0 *
1#
#10000
0#
#15000
1#
#20000
0#
1$
0'
#25000
1#
#30000
0#
1&
#35000
b1 +
b1 (
1#
#40000
0#
1%
#45000
b1 +
b11 (
b1 )
1"
b1 !
b1 *
1#
#50000
0#
0&
#55000
b1 +
b10 !
b10 *
b10 (
b11 )
1#
#60000
0#
0%
#65000
b1 +
b0 (
b10 )
b11 !
b11 *
1#
#70000
0#
#75000
b0 +
b100 !
b100 *
b0 )
1#
